AthenaMock/__init__.py
AthenaMock/functions/__init__.py
AthenaMock/functions/generators_seed.py
AthenaMock/passwords/__init__.py
AthenaMock/passwords/functions/__init__.py
AthenaMock/passwords/functions/generators.py
AthenaMock/usernames/__init__.py
AthenaMock/usernames/data/__init__.py
AthenaMock/usernames/data/enclosing.py
AthenaMock/usernames/data/end.py
AthenaMock/usernames/data/names.py
AthenaMock/usernames/data/seperations.py
AthenaMock/usernames/functions/__init__.py
AthenaMock/usernames/functions/generators.py
AthenaMock-0.2.0.dist-info/LICENSE
AthenaMock-0.2.0.dist-info/METADATA
AthenaMock-0.2.0.dist-info/WHEEL
AthenaMock-0.2.0.dist-info/top_level.txt
AthenaMock-0.2.0.dist-info/RECORD
